{
  "main": {
    "name":"Emelia Jarnot",
    "description":"Full Stack Developer",
    "image":"selfie4.jpg",
    "bio":"I am a fullstack developer based in Portland, OR. I have fallen in love with coding and feel at home in its logic. I especially love problem solving within JavaScript. Both finding and squashing bugs and using the JavaScript language to answer and solve puzzles are things I especially enjoy!",
    "contactmessage":"Here is where you should write your message to readers to have them get in contact with you.",
    "email": "ejarnot42@outlook.com",
    "phone": "425-387-2867",
    "github":"https://github.com/ejarnot",
    "linkedin":"https://www.linkedin.com/in/emelia-jarnot-928864234/",
    "codewars": "https://www.codewars.com/users/ejarnot",
    "address":{
      "city":"Portland",
      "state":"OR",
      "zip": "97206"
    },
    "website": "http://www.timbakerdev.com",
    "resumedownload":"https://docs.google.com/document/d/e/2PACX-1vRbifBtbE-II6p-wT3LJWtSmITXMUbv9nEVtR7RwhpSvXmavSH6GGq6M1FToGbur_lj5TlIHIgwykJe/pub",
    "social":[
      {
        "name":"linkedin",
        "url":"https://www.linkedin.com/in/emelia-jarnot-928864234/",
        "className":"fa fa-linkedin"
      },
      {
        "name":"github",
        "url":"https://github.com/ejarnot",
        "className":"fa fa-github"
      }
    ]
  },
  "resume":{
    "skillmessage":"Main experience in front end development within HTML, CSS, JavaScript, and React. I have some knowledge of backend REST APIs within Node.js, Express.js, and SQL. I also have a basic knowledge of working within Visual Studio Code, Github, and Postman ",
    "education":[
      {
        "school":"TrueCoders",
        "degree":"Web Development Bootcamp",
        "graduated":"May 2022",
        "description":"Spent time in an intensive, 9 week, course learning both the front end browser side of building websites, with HTML, CSS, JavaScript, and React; and the backend through the JavaScript lens with Node and Express. Spent time learning how to build tables and write queries in SQL."
      },
      {
        "school":"Willamette University",
        "degree":"BA in Sociology",
        "graduated":"May 2013",
        "description":"Studied sociology for 4 years at a small liberal arts college located in the Willamette Valley. Focused my studies on postmodern theory and how it relates to our interactions and identities on social media. "
      }
    ],
    "work":[
      {
        "company":"Awesome Design Studio",
        "title":"Senior UX God ",
        "years":"March 2018 - Present",
        "description":"Describe work, special projects, notable achievements, what technologies you have been working with, and anything else that would be useful for an employer to know."
      },
      {
        "company":"Super Cool Studio",
        "title":"Junior bug fixer",
        "years":"March 2017 - February 2018",
        "description":"Describe work, special projects, notable achievements, what technologies you have been working with, and anything else that would be useful for an employer to know."
      }
    ],
    "skills":[
      {
        "name":"HTML",
        "level":"90%"
      },
      {
        "name":"CSS",
        "level":"85%"
      },
      {
        "name":"JavaScript",
        "level":"90%"
      },
      {
        "name":"ReactJS",
        "level":"70%"
      },
      {
        "name":"NodeJS",
        "level":"65%"
      },
      {
        "name":"ExpressJS",
        "level":"65%"
      },
      {
        "name":"MySQL",
        "level":"70%"
      }
    ]
  },
  "portfolio":{
    "projects": [
      {
        "title":"Canadian Wanderlust",
        "category":"My Travel Blog for my post-university travels",
        "image":"01.jpg",
        "url":"https://www.canadianwanderlust.com"
      },
      {
        "title":"Fury Fighting Gear",
        "category":"(offline now) A fighting gear company I started",
        "image":"02.jpg",
        "url":"http://www.timbakerdev.com"
      },
      {
        "title":"Original Thai Food",
        "category":"Website I built for a restaurant I like in Thailand",
        "image":"03.jpg",
        "url":"http://www.timbakerdev.com/originalthaifood.github.io"
      },
      {
        "title":"Resume Website",
        "category":"A React based resume website template",
        "image":"04.jpg",
        "url":"http://www.timbakerdev.com"
      },
      {
        "title":"Smirkspace",
        "category":"(MVP Only) A React and Meteor based chat University project.",
        "image":"05.jpg",
        "url":"http://www.smirkspace.com"
      },
      {
        "title":"Canadian Wanderlust",
        "category":"My Travel Blog for my post-university travels",
        "image":"06.jpg",
        "url":"https://www.canadianwanderlust.com"
      },
      {
        "title":"Fury Fighting Gear",
        "category":"(offline now) A fighting gear company I started",
        "image":"01.jpg",
        "url":"http://www.timbakerdev.com"
      },
      {
        "title":"Original Thai Food",
        "category":"Website I built for a restaurant I like in Thailand",
        "image":"02.jpg",
        "url":"http://www.timbakerdev.com/originalthaifood.github.io"
      },
      {
        "title":"Original Thai Food",
        "category":"Website I built for a restaurant I like in Thailand",
        "image":"03.jpg",
        "url":"http://www.timbakerdev.com/originalthaifood.github.io"
      },
      {
        "title":"Resume Website",
        "category":"A React based resume website template",
        "image":"04.jpg",
        "url":"http://www.timbakerdev.com"
      },
      {
        "title":"Smirkspace",
        "category":"(MVP Only) A React and Meteor based chat University project.",
        "image":"05.jpg",
        "url":"http://www.smirkspace.com"
      },
      {
        "title":"Canadian Wanderlust",
        "category":"My Travel Blog for my post-university travels",
        "image":"06.jpg",
        "url":"https://www.canadianwanderlust.com"
      }
    ]
  }
}
